{
  "Rey Castillo Garc\u00eda": {
    "display": "bottom",
    "color": "5721EC",
    "lines": {
      "a18": {
        "lineref": "a18",
        "start": 0,
        "stop": 0,
        "value": "Nda\u00b3tu&#039;\u2074un\u2074 lu\u00b3chi&#039;\u2074i\u00b2=un\u2074 ji&#039;\u2074in\u2074=ndu\u00b2 xa&#039;\u00b9a\u2074 i\u00b3ta\u00b2 sa\u00b3in\u2074 ta\u00b3ta\u00b2 chi\u00b9."
      },
      "a19": {
        "lineref": "a19",
        "start": 7.1,
        "stop": 7.1,
        "value": "Sa\u00b9a\u00b3 nu\u00b9\u2074u\u00b3 ba\u2074\u00b2 i\u2074yo\u00b2 tan\u00b3 sa\u00b9a\u00b3, nda\u2074a\u00b2 ba\u2074\u00b2 chi&#039;\u2074i\u2074=na\u207d\u00b2\u207e=e\u00b2 nda\u2074a\u00b2 tiem\u2074pu\u00b2 chi&#039;\u2074i\u2074=na\u207d\u00b2\u207e=e\u00b2"
      },
      "a20": {
        "lineref": "a20",
        "start": 11.972,
        "stop": 11.972,
        "value": "na\u2074chu\u00b3 jo\u2074ndo\u00b9\u00b3=a\u00b2 ji&#039;\u2074in\u2074=na\u00b2, sa\u00b9a\u00b3 i\u2074in\u207d\u2074\u207e=a\u00b2 chi\u00b9 tan\u00b3 na\u2074chu\u00b3 jo\u2074ndo\u00b9\u00b3=a\u00b2 chi\u00b9."
      },
      "a27": {
        "lineref": "a27",
        "start": 57.621,
        "stop": 57.621,
        "value": "\u00bfAn\u2074 ki\u2074ku\u00b9\u00b3=na\u207d\u00b3\u207e=e\u00b3?"
      },
      "a29": {
        "lineref": "a29",
        "start": 64.875,
        "stop": 64.875,
        "value": "\u00bfAn\u2074 xa&#039;\u2074an\u00b2 bi\u00b9xi\u207d\u00b9\u207e=a\u00b9?"
      },
      "a33": {
        "lineref": "a33",
        "start": 79.697,
        "stop": 79.697,
        "value": "An\u2074 sa\u00b3kan\u2074 ba\u00b3. Tan\u2074\u00b2 i\u2074yo\u00b2, ya\u00b9 ba\u2074li\u2074 ba\u2074\u00b2 kan\u2074. Tan\u00b3 ki\u2074ku\u00b9\u00b3=na\u207d\u00b2\u207e=e\u00b2 tan\u00b3, ya\u00b9kan\u00b3, tan\u00b3 \u00bfsa\u00b9a\u00b3 i\u2074xa\u00b3=na\u00b2 nda\u2074-ka\u00b3ya\u00b2=na\u00b9 ta\u00b3ta\u00b2 tin\u00b3?"
      },
      "a36": {
        "lineref": "a36",
        "start": 96.045,
        "stop": 96.045,
        "value": "Tan\u00b3 \u00bfan\u2074 a\u00b9su\u00b3 in\u00b3ka\u2074chi\u00b9 chi&#039;\u2074i\u2074=na\u207d\u00b2\u207e=e\u00b2 ji&#039;\u2074in\u2074, ya\u00b9kan\u00b3 ...? I\u00b3in\u00b3 tiem\u2074pu\u00b2. An\u2074 sa\u00b3kan\u2074 ba\u00b3."
      },
      "a39": {
        "lineref": "a39",
        "start": 111.448,
        "stop": 111.448,
        "value": "Ba\u00b9\u2074\u00b3 xi\u2074yo\u00b9\u00b3=a\u00b2 yu\u00b3mi\u2074."
      },
      "a42": {
        "lineref": "a42",
        "start": 117.752,
        "stop": 117.752,
        "value": "An\u2074 sa\u00b3kan\u2074 ba\u00b3 te\u00b9. Tan\u00b3 ya\u00b9kan\u00b3, sa\u00b3kan\u2074 ku\u2074u\u2074 ndi&#039;\u00b3i\u00b3 ba\u207d\u00b3\u207e=e\u00b2 ran\u2074. Ba&#039;\u00b9a\u00b3."
      },
      "a43": {
        "lineref": "a43",
        "start": 124.14,
        "stop": 124.14,
        "value": "\u00bfSa\u00b9a\u00b3 na\u00b3ni\u207d\u2074\u207e=un\u2074?"
      },
      "a45": {
        "lineref": "a45",
        "start": 127.012,
        "stop": 127.012,
        "value": "\u00bfSa\u00b9a\u00b3 kwi\u00b9ya\u207d\u00b9\u207e=on\u2074?"
      },
      "a47": {
        "lineref": "a47",
        "start": 130.175,
        "stop": 131.876,
        "value": "\u00bfSa\u00b9a\u00b3 na\u00b3ni\u2074 \u00f1u\u00b3u\u00b2=un\u2074?"
      },
      "a49": {
        "lineref": "a49",
        "start": 132.305,
        "stop": 132.313,
        "value": "Ba&#039;\u00b9a\u00b3 ba\u00b3."
      }
    }
  },
  "Rey Castillo Garc\u00eda Surface-2": {
    "display": "nodisplay",
    "color": "3C4EF1",
    "lines": {
      "a18_SURFACE2": {
        "lineref": "a18_SURFACE2",
        "start": 0,
        "stop": 7.1,
        "value": "Nda\u00b3t\u0169&#039;\u2074\u0169\u2074 lu\u00b3ch\u1ef9\u0169&#039;\u2074\u0169\u00b2\u2074 j\u0129&#039;\u2074\u0129\u2074ndu\u00b2 xa&#039;\u00b9a\u2074 i\u00b3ta\u00b2 s\u00e3\u00b3\u0129\u2074 ta\u00b3ta\u00b2 chi\u00b9."
      },
      "a19_SURFACE2": {
        "lineref": "a19_SURFACE2",
        "start": 7.1,
        "stop": 11.972,
        "value": "Sa\u00b9a\u00b3 n\u0169\u00b9\u2074\u0169\u00b3 ba\u2074\u00b2 i\u2074yo\u00b2 t\u00e3\u00b3 sa\u00b9a\u00b3, nda\u2074a\u00b2 ba\u2074\u00b2 chi&#039;\u2074i\u2074n\u1ebd\u00b2 nda\u2074a\u00b2 tyem\u2074pu\u00b2 chi&#039;\u2074i\u2074n\u1ebd\u00b2."
      },
      "a20_SURFACE2": {
        "lineref": "a20_SURFACE2",
        "start": 11.972,
        "stop": 16.909,
        "value": "n\u00e3\u2074chu\u00b3 jo\u2074ndwa\u00b9\u00b3\u00b2 j\u0129&#039;\u2074\u0129\u2074n\u00e3\u00b2, sa\u00b9a\u00b3 \u1ef9\u00e3\u2074\u00e3\u00b2 chi\u00b9 t\u00e3\u00b3 n\u00e3\u2074chu\u00b3 jo\u2074ndwa\u00b9\u00b3\u00b2 chi\u00b9."
      },
      "a27_SURFACE2": {
        "lineref": "a27_SURFACE2",
        "start": 57.621,
        "stop": 58.351,
        "value": "\u00bfAn\u2074 ki\u2074ku\u00b9\u00b3n\u1ebd\u00b3?"
      },
      "a29_SURFACE2": {
        "lineref": "a29_SURFACE2",
        "start": 64.875,
        "stop": 65.885,
        "value": "\u00bfAn\u2074 x\u00e3&#039;\u2074\u00e3\u00b2 bi\u00b9xya\u00b9?"
      },
      "a33_SURFACE2": {
        "lineref": "a33_SURFACE2",
        "start": 79.697,
        "stop": 86.903,
        "value": "An\u2074 sa\u00b3k\u00e3\u2074 ba\u00b3. T\u00e3\u2074\u00b2 i\u2074yo\u00b2 ya\u00b9 ba\u2074li\u2074 ba\u2074\u00b2 k\u00e3\u2074. T\u00e3\u00b3 ki\u2074ku\u00b9\u00b3n\u1ebd\u00b2 t\u00e3\u00b3, ya\u00b9k\u00e3\u00b3, t\u00e3\u00b3 \u00bfsa\u00b9a\u00b3 i\u2074xa\u00b3n\u00e3\u00b2 nda\u2074ka\u00b3ya\u00b2n\u00e3\u00b9 ta\u00b3ta\u00b2 t\u0129\u00b3?"
      },
      "a36_SURFACE2": {
        "lineref": "a36_SURFACE2",
        "start": 96.045,
        "stop": 104.113,
        "value": "T\u00e3\u00b3 \u00bf\u00e3\u2074 a\u00b9su\u00b3 \u0129\u00b3ka\u2074chi\u00b9 chi&#039;\u2074i\u2074n\u1ebd\u00b2 j\u0129&#039;\u2074\u0129\u2074, ya\u00b9k\u00e3\u00b3 ...?  I\u00b3\u0129\u00b3 tyem\u2074pu\u00b2. An\u2074 sa\u00b3k\u00e3\u2074 ba\u00b3."
      },
      "a39_SURFACE2": {
        "lineref": "a39_SURFACE2",
        "start": 111.448,
        "stop": 113.478,
        "value": "Ba\u00b9\u2074\u00b3 xi\u2074ywa\u00b9\u00b3\u00b2 yu\u00b3m\u0129\u2074."
      },
      "a42_SURFACE2": {
        "lineref": "a42_SURFACE2",
        "start": 117.752,
        "stop": 124.14,
        "value": "An\u2074 sa\u00b3k\u00e3\u2074 ba\u00b3 te\u00b9. T\u00e3\u00b3 ya\u00b9k\u00e3\u00b3, sa\u00b3k\u00e3\u2074 ku\u2074u\u2074 ndi&#039;\u00b3i\u00b3 be\u00b2 r\u00e3\u2074. Ba&#039;\u00b9a\u00b3."
      },
      "a43_SURFACE2": {
        "lineref": "a43_SURFACE2",
        "start": 124.14,
        "stop": 127.012,
        "value": "\u00bfSa\u00b9a\u00b3 n\u00e3\u00b3n\u1ef9\u0169\u2074?"
      },
      "a45_SURFACE2": {
        "lineref": "a45_SURFACE2",
        "start": 127.012,
        "stop": 130.175,
        "value": "\u00bfSa\u00b9a\u00b3 kwi\u00b9\u1ef9\u00f5\u2074?"
      },
      "a47_SURFACE2": {
        "lineref": "a47_SURFACE2",
        "start": 130.175,
        "stop": 132.305,
        "value": "\u00bfSa\u00b9a\u00b3 n\u00e3\u00b3n\u0129\u2074 \u00f1\u0169\u00b3\u0169\u00b2\u2074?"
      },
      "a49_SURFACE2": {
        "lineref": "a49_SURFACE2",
        "start": 132.313,
        "stop": 134.468,
        "value": "Ba&#039;\u00b9a\u00b3 ba\u00b3."
      }
    }
  },
  "Ra\u00fal Felipe Margarito": {
    "display": "bottom",
    "color": "C10FF7",
    "lines": {
      "a21": {
        "lineref": "a21",
        "start": 16.909,
        "stop": 16.909,
        "value": "I\u00b3ta\u00b2 sa\u00b3in\u2074 ta\u00b3ta\u00b2 kan\u2074 ba\u2074\u00b2 ya\u00b9, ya\u00b9 ka\u2074chi\u00b2=o\u2074 ndo\u2074ko\u00b3to\u207d\u00b3\u207e=e\u2074 ji&#039;\u2074in\u2074 i\u00b3ta\u00b2 kwa\u00b9on\u2074 ka\u2074chi\u00b2=o\u2074 ya\u00b9 bi\u00b3ko\u2074 i\u00b3ta\u00b2,"
      },
      "a22": {
        "lineref": "a22",
        "start": 24.331,
        "stop": 24.331,
        "value": "ya\u00b9 chi&#039;\u2074i\u2074=na\u207d\u00b2\u207e=e\u00b2 kan\u2074 ndi\u2074 a\u00b9su\u00b3 tiem\u2074pu\u00b2 ka\u00b3ta\u00b2=e\u2074 tun\u2074 i\u00b3ta\u00b2 kwa\u00b9on\u2074 i\u00b3kan\u2074 ba\u2074\u00b2 chi\u00b3..., ka\u00b3ta\u00b2 tu\u207d\u00b3\u207e=e\u2074 ya\u00b9 kan\u2074 ndi\u00b3kin\u2074=a\u00b2 kan\u2074 tan\u00b3"
      },
      "a23": {
        "lineref": "a23",
        "start": 31.243,
        "stop": 31.243,
        "value": "Xi\u00b9\u2074in\u00b3=ni\u2074\u00b2 bi\u2074=a\u00b2 ko\u00b3o\u207d\u00b3\u207e=a\u00b2 \u00f1u\u00b3u\u00b2=e\u2074 ka\u00b9a\u00b3 ndi\u2074 ba\u00b3 ba\u00b9\u2074\u00b3 ndu\u2074ta&#039;\u00b3an\u207d\u00b2\u207e=e\u00b2 ko\u00b3o\u207d\u00b3\u207e=a\u00b2 ka\u00b9a\u00b3 ndi\u2074 \u00f1u\u00b3u\u00b2 ja\u00b9, an\u2074 \u00f1u\u00b3u\u00b2 sa&#039;\u2074an\u2074 ba\u2074\u00b2 an\u2074 \u00f1u\u00b3u\u00b2 bi\u00b9xin\u00b3 ka\u00b9 i\u00b3kan\u2074 ba\u2074\u00b2 la\u00b3tun\u2074 xi\u2074yo\u00b9\u00b3=a\u00b2 tan\u00b3 \u00f1u\u00b3u\u00b2=e\u2074 ka\u00b9a\u00b3 ndi\u2074 kwa\u2074chi\u00b3=ni\u2074\u00b2 xa&#039;\u2074nu\u00b3=run\u2074 tu\u2074u\u00b2=yu\u00b9."
      },
      "a24": {
        "lineref": "a24",
        "start": 40.327,
        "stop": 40.327,
        "value": "So&#039;\u00b3o\u00b3 so&#039;\u00b3o\u00b3 ti\u2074 ba\u00b3 xa&#039;\u2074nu\u00b3=run\u2074 tan\u00b3 i\u2074yo\u00b2 i\u00b3ta\u00b2=run\u2074, ba\u2074li\u2074=ni\u2074\u00b2 nu\u00b9\u2074u\u207d\u00b3\u207e=a\u00b2 so&#039;\u00b3o\u00b3 so&#039;\u00b3o\u00b3 ti\u2074 ba\u2074li\u2074 nu\u00b9\u2074u\u207d\u00b3\u207e=a\u00b2 tan\u00b3"
      },
      "a25": {
        "lineref": "a25",
        "start": 46.041,
        "stop": 46.041,
        "value": "ya\u00b9 kan\u2074 ba\u2074\u00b2 kwa&#039;\u00b9an\u00b9 ji&#039;\u2074in\u207d\u2074\u207e=o\u2074 pa\u00b3san\u2074tu\u00b2 ndo\u00b3ko\u00b3to\u207d\u00b3\u207e=e\u2074 ji&#039;\u2074in\u2074 i\u00b3ta\u00b2 kwa\u00b9on\u2074 na\u2074tu\u00b2 i\u2074yo\u207d\u00b2\u207e=a\u00b2 xa\u00b3ku\u2074=ni\u2074\u00b2 ba\u2074\u00b2 xi\u2074yo\u00b9\u00b3=a\u00b2 \u00f1u\u00b3u\u00b2 ka\u00b9a\u00b3. Ko\u00b9\u2074o\u00b3 ba&#039;\u00b9a\u00b3 ba&#039;\u00b9a\u00b3=e\u00b2 kan\u2074 \u00f1u\u00b3u\u00b2 ka\u00b9a\u00b3 ndi\u2074,"
      },
      "a26": {
        "lineref": "a26",
        "start": 53.917,
        "stop": 53.917,
        "value": "an\u2074 ba\u00b9\u2074\u00b3 chi&#039;\u2074i\u2074=na\u207d\u00b2\u207e=e\u00b2 an\u2074 ko\u00b9\u2074o\u00b3 ni\u00b3 mi\u00b3i\u2074=\u00b2 tan\u00b3 ba\u00b9\u2074\u00b3 chi&#039;\u2074i\u207d\u2074\u207e=a\u00b2 a\u00b9chi\u00b9 ndi\u2074 ta\u00b3ta\u207d\u00b2\u207e=e\u00b2 ku\u2074ni\u207d\u00b2\u207e=a\u00b2."
      },
      "a28": {
        "lineref": "a28",
        "start": 58.351,
        "stop": 58.351,
        "value": "Ki\u2074ku\u00b9\u00b3=na\u207d\u00b2\u207e=e\u00b2 ji&#039;\u2074in\u2074 yo&#039;\u00b3o\u2074 ki\u2074ku\u00b9\u00b3=na\u207d\u00b3\u207e=e\u00b3. Ni\u2074i\u00b2\u2074 chi&#039;\u2074i\u00b2 so&#039;\u00b3o\u00b3 so&#039;\u00b3o\u00b3 ti\u2074 yo&#039;\u00b3o\u2074=a\u00b2 ya\u00b9 sa\u00b3kan\u2074 ku\u2074u\u207d\u2074\u207e=a\u00b2 ya\u00b9 i\u00b3ta\u00b2 ba\u2074li\u2074=ni\u2074\u00b2 ba\u2074\u00b3."
      },
      "a30": {
        "lineref": "a30",
        "start": 65.885,
        "stop": 65.885,
        "value": "Xa&#039;\u2074an\u00b2 bi\u00b9xi\u00b9 ta&#039;\u00b3an\u207d\u00b2\u207e=e\u00b2, xa&#039;\u2074an\u00b2 bi\u00b9xi\u207d\u00b9\u207e=a\u00b9 ba&#039;\u00b9a\u00b3 xi\u00b3ko\u00b2 ba\u207d\u00b3\u207e=e\u00b2 ku&#039;\u00b9un\u00b9 ji&#039;\u2074in\u207d\u2074\u207e=o\u2074 ndo\u00b3ko\u00b3to\u207d\u00b3\u207e=e\u2074."
      },
      "a31": {
        "lineref": "a31",
        "start": 70.611,
        "stop": 70.611,
        "value": "I\u00b3ta\u00b2 ndi\u00b9\u2074i\u00b2 ba\u2074\u00b2 kan\u2074, i\u2074yo\u207d\u00b2\u207e=a\u00b2 ndi\u00b9\u2074i\u00b2 i\u2074yo\u207d\u00b2\u207e=a\u00b2 kwa&#039;\u2074a\u00b9, u\u00b9bi\u00b9 nu\u00b9\u2074u\u00b3 tu\u00b3 ba\u2074\u00b2 kan\u2074 ba\u00b3."
      },
      "a32": {
        "lineref": "a32",
        "start": 75.889,
        "stop": 75.889,
        "value": "Tan\u2074\u00b2 ku\u2074ni\u00b2 ko\u00b3o\u00b3 yu\u00b9ku\u00b9 tun\u2074 i\u00b3ta\u00b2 <i>pastora</i> sa\u00b3kan\u2074 ku\u2074ni\u00b2 ko\u00b3o\u00b3 tu\u00b3 yu\u00b9ku\u00b9 tun\u2074 kan\u2074 ba\u00b3."
      },
      "a34": {
        "lineref": "a34",
        "start": 79.697,
        "stop": 86.903,
        "value": "A\u00b9be\u00b3, sa\u00b3kan\u2074 i\u2074in\u207d\u2074\u207e=a\u00b2 ya\u00b9 kwi\u2074i\u00b2\u2074 ba\u2074li\u2074 ba\u2074\u00b2 kan\u2074."
      },
      "a35": {
        "lineref": "a35",
        "start": 86.903,
        "stop": 86.903,
        "value": "Ndi\u00b3kin\u2074=a\u00b2 kan\u2074 nda\u2074-ka\u00b3ya\u00b2=na\u00b9 tu\u2074u\u00b2=yu\u00b9 a\u00b9chi\u00b9 ndi\u2074 ta&#039;\u00b9\u2074an\u00b2 chi&#039;\u00b3i\u207d\u00b3\u207e=a\u00b2. A\u00b9chi\u00b9 ndi\u2074 ya\u00b9 i\u2074yo\u00b2 ndi\u00b3kin\u2074 ba\u2074\u00b2 mi\u2074i\u2074 i\u2074yo\u00b2, mi\u2074i\u2074 i\u2074yo\u00b2 i\u00b3ta\u207d\u00b2\u207e=e\u00b2 kan\u2074 i\u00b3kan\u2074 ndo\u2074o\u00b9\u00b3=a\u00b2 i\u2074chi\u207d\u00b9\u207e=a\u00b9 tan\u00b3 i\u00b3kan\u2074 nda\u00b3-ka\u00b3ya\u00b2=na\u207d\u00b9\u207e=e\u00b9 ko\u2074..., ko\u2074ndo\u207d\u00b3\u207e=a\u00b2 ta\u00b3ta\u00b2=na\u00b9."
      },
      "a37": {
        "lineref": "a37",
        "start": 96.045,
        "stop": 104.113,
        "value": "In\u00b3ka\u2074chi\u00b9 chi&#039;\u2074i\u2074=na\u207d\u00b2\u207e=e\u00b2 ji&#039;\u2074in\u2074 tun\u2074 i\u00b3ta\u00b2 kwa\u00b9on\u2074 ba\u00b3 tu\u2074u\u00b2=yu\u00b9, i\u00b3in\u00b3 tiem\u2074pu\u00b2."
      },
      "a38": {
        "lineref": "a38",
        "start": 104.113,
        "stop": 104.113,
        "value": "I\u00b3in\u00b3 tiem\u2074pu\u00b2 ya\u00b9 kan\u2074 ndi\u2074 ndu\u2074ta\u207d\u00b9\u207e=e\u00b9 tan\u00b3 ja\u2074chiu\u2074un\u207d\u2074\u207e=a\u00b2 ji&#039;\u2074in\u2074=na\u00b2 ya\u00b9, ya\u00b9 bi\u00b3ko\u2074 i\u00b3ta\u00b2 ka\u2074chi\u00b2=o\u2074 kan\u2074 a\u00b9chi\u00b9, sa\u00b3kan\u2074 ba\u2074\u00b2 ji\u2074ni\u00b2 yu&#039;\u00b9u\u00b9 ba\u207d\u00b3\u207e=e\u00b2 ran\u2074, ko\u00b9\u2074o\u207d\u00b3\u207e=a\u00b2 ji\u2074ni\u00b2=yu\u00b9 tiem\u2074pu\u00b2 bi\u00b3tin\u00b3 ndi\u2074,"
      },
      "a40": {
        "lineref": "a40",
        "start": 111.448,
        "stop": 113.478,
        "value": "Ba\u00b9\u2074\u00b3 xi\u2074yo\u00b9\u00b3=a\u00b2 yu\u00b3mi\u2074."
      },
      "a41": {
        "lineref": "a41",
        "start": 113.478,
        "stop": 113.478,
        "value": "Ji\u00b9\u2074ni\u00b2=o\u2074 sa\u00b9a\u00b3 a\u00b3sa\u207d\u00b3\u207e=e\u00b2 na\u2074 i\u2074yo\u00b2 ndi\u00b3kin\u2074=a\u00b2 tan\u00b3 chi&#039;\u00b3i\u207d\u00b3\u207e=o\u2074=e\u00b2 ndi\u2074 xa\u00b3ku\u2074=ni\u2074\u00b2 xi\u2074yo\u00b9\u00b3=a\u00b2 \u00f1u\u00b3u\u00b2=e\u2074 ka\u00b9a\u00b3."
      },
      "a44": {
        "lineref": "a44",
        "start": 124.14,
        "stop": 127.012,
        "value": "Ra\u00fal na\u00b3ni\u2074=\u00b2."
      },
      "a46": {
        "lineref": "a46",
        "start": 127.012,
        "stop": 130.175,
        "value": "U\u00b9bi\u00b9 xi\u00b3ko\u00b3 i\u00b9\u00f1u\u00b9 kwi\u00b9ya\u00b9 ku\u2074u\u207d\u2074\u207e=\u00b2."
      },
      "a48": {
        "lineref": "a48",
        "start": 130.175,
        "stop": 132.313,
        "value": "Yolox\u00f3chitl ku\u2074u\u2074 \u00f1u\u00b3u\u00b2=yu\u00b9."
      }
    }
  },
  "Ra\u00fal Felipe Margarito Surface-2": {
    "display": "nodisplay",
    "color": "5927BB",
    "lines": {
      "a21_SURFACE2": {
        "lineref": "a21_SURFACE2",
        "start": 16.909,
        "stop": 24.331,
        "value": "I\u00b3ta\u00b2 s\u00e3\u00b3\u0129\u2074 ta\u00b3ta\u00b2 k\u00e3\u2074 ba\u2074\u00b2 ya\u00b9, ya\u00b9 ka\u2074chyo\u00b2\u2074 ndo\u2074ko\u00b3twe\u2074 j\u0129&#039;\u2074\u0129\u2074 i\u00b3ta\u00b2 kw\u00e3\u00b9\u00f5\u2074 ka\u2074chyo\u00b2\u2074 ya\u00b9 bi\u00b3ko\u2074 i\u00b3ta\u00b2,"
      },
      "a22_SURFACE2": {
        "lineref": "a22_SURFACE2",
        "start": 24.331,
        "stop": 31.243,
        "value": "ya\u00b9 chi&#039;\u2074i\u2074n\u1ebd\u00b2 k\u00e3\u2074 ndi\u2074 a\u00b9su\u00b3 tyem\u2074pu\u00b2 ka\u00b3te\u00b2\u2074 t\u0169\u2074 i\u00b3ta\u00b2 kw\u00e3\u00b9\u00f5\u2074 i\u00b3k\u00e3\u2074 ba\u2074\u00b2 chi\u00b3..., ka\u00b3ta\u00b2 twe\u2074 ya\u00b9 k\u00e3\u2074 ndi\u00b3k\u1ef9\u00e3\u2074\u00b2 k\u00e3\u2074 t\u00e3\u00b3"
      },
      "a23_SURFACE2": {
        "lineref": "a23_SURFACE2",
        "start": 31.243,
        "stop": 40.327,
        "value": "X\u0129\u00b9\u2074\u0129n\u00b3=ni\u2074\u00b2 bya\u2074\u00b2 kwa\u00b3a\u00b2 nywe\u00b3e\u00b2\u2074 ka\u00b9a\u00b3 ndi\u2074 ba\u00b3 ba\u00b9\u2074\u00b3 ndu\u2074t\u1ebd&#039;\u00b3\u1ebd\u00b2 kwa\u00b3a\u00b2 ka\u00b9a\u00b3 ndi\u2074 \u00f1\u0169\u00b3\u0169\u00b2 ja\u00b9, \u00e3\u2074 \u00f1\u0169\u00b3\u0169\u00b2 s\u00e3&#039;\u2074\u00e3\u2074 ba\u2074\u00b2 \u00e3\u2074 \u00f1\u0169\u00b3\u0169\u00b2 bi\u00b9x\u0129\u00b3 ka\u00b9 i\u00b3k\u00e3\u2074 ba\u2074\u00b2 la\u00b3t\u0169\u2074 xi\u2074ywa\u00b9\u00b3\u00b2 t\u00e3\u00b3 nywe\u00b3e\u00b2\u2074 ka\u00b9a\u00b3 ndi\u2074 kwa\u2074chi\u00b3n\u0129\u2074\u00b2 xa&#039;\u2074n\u0169\u00b3r\u0169\u2074 tu\u2074u\u00b2yu\u00b9."
      },
      "a24_SURFACE2": {
        "lineref": "a24_SURFACE2",
        "start": 40.327,
        "stop": 46.041,
        "value": "So&#039;\u00b3o\u00b3 so&#039;\u00b3o\u00b3 ti\u2074 ba\u00b3 xa&#039;\u2074n\u0169\u00b3r\u0169\u2074 t\u00e3\u00b3 i\u2074yo\u00b2 i\u00b3ta\u00b2r\u0169\u2074, ba\u2074li\u2074n\u0129\u2074\u00b2 nw\u0303\u00e3\u00b9\u2074\u00e3\u00b2 so&#039;\u00b3o\u00b3 so&#039;\u00b3o\u00b3 ti\u2074 ba\u2074li\u2074 nw\u0303\u00e3\u00b9\u2074\u00e3\u00b2 t\u00e3\u00b3"
      },
      "a25_SURFACE2": {
        "lineref": "a25_SURFACE2",
        "start": 46.041,
        "stop": 53.917,
        "value": "ya\u00b9 k\u00e3\u2074 ba\u2074\u00b2 kw\u00e3&#039;\u00b9\u00e3\u00b9 jyo&#039;\u2074o\u2074 pa\u00b3s\u00e3\u2074tu\u00b2 ndo\u00b3ko\u00b3twe\u2074 j\u0129&#039;\u2074\u0129\u2074 i\u00b3ta\u00b2 kw\u00e3\u00b9\u00f5\u2074 n\u00e3\u2074tu\u00b2 i\u2074ywa\u00b2 xa\u00b3ku\u2074n\u0129\u2074\u00b2 ba\u2074\u00b2 xi\u2074ywa\u00b9\u00b3\u00b2 \u00f1\u0169\u00b3\u0169\u00b2 ka\u00b9a\u00b3. Ko\u00b9\u2074o\u00b3 ba&#039;\u00b9a\u00b3 be&#039;\u00b9e\u00b3\u00b2 k\u00e3\u2074 \u00f1\u0169\u00b3\u0169\u00b2 ka\u00b9a\u00b3 ndi\u2074,"
      },
      "a26_SURFACE2": {
        "lineref": "a26_SURFACE2",
        "start": 53.917,
        "stop": 57.621,
        "value": "\u00e3\u2074 ba\u00b9\u2074\u00b3 chi&#039;\u2074i\u2074n\u1ebd\u00b2 \u00e3\u2074 ko\u00b9\u2074o\u00b3 n\u0129\u00b3 m\u0129\u00b3\u0129\u2074\u00b2 t\u00e3\u00b3 ba\u00b9\u2074\u00b3 chya&#039;\u2074a\u00b2 a\u00b9chi\u00b9 ndi\u2074 ta\u00b3te\u00b2 ku\u2074n\u1ef9\u00e3\u00b2."
      },
      "a28_SURFACE2": {
        "lineref": "a28_SURFACE2",
        "start": 58.351,
        "stop": 64.875,
        "value": "Ki\u2074ku\u00b9\u00b3n\u1ebd\u00b2 j\u0129&#039;\u2074\u0129\u2074 yo&#039;\u00b3o\u2074 ki\u2074ku\u00b9\u00b3n\u1ebd\u00b3. Ni\u2074i\u00b2\u2074 chi&#039;\u2074i\u00b2 so&#039;\u00b3o\u00b3 so&#039;\u00b3o\u00b3 ti\u2074 ywa&#039;\u00b3a\u2074\u00b2 ya\u00b9 sa\u00b3k\u00e3\u2074 kwa\u2074a\u00b2 ya\u00b9 i\u00b3ta\u00b2 ba\u2074li\u2074n\u0129\u2074\u00b2 ba\u2074\u00b3."
      },
      "a30_SURFACE2": {
        "lineref": "a30_SURFACE2",
        "start": 65.885,
        "stop": 70.611,
        "value": "X\u00e3&#039;\u2074\u00e3\u00b2 bi\u00b9xi\u00b9 t\u1ebd&#039;\u00b3\u1ebd\u00b2, x\u00e3&#039;\u2074\u00e3\u00b2 bi\u00b9xya\u00b9 ba&#039;\u00b9a\u00b3 xi\u00b3ko\u00b2 be\u00b2 k\u0169&#039;\u00b9\u0169\u00b9 jyo&#039;\u2074o\u2074 ndo\u00b3ko\u00b3twe\u2074."
      },
      "a31_SURFACE2": {
        "lineref": "a31_SURFACE2",
        "start": 70.611,
        "stop": 75.889,
        "value": "I\u00b3ta\u00b2 ndi\u00b9\u2074i\u00b2 ba\u2074\u00b2 k\u00e3\u2074, i\u2074ywa\u00b2 ndi\u00b9\u2074i\u00b2 i\u2074ywa\u00b2 kwa&#039;\u2074a\u00b9, u\u00b9bi\u00b9 n\u0169\u00b9\u2074\u0169\u00b3 tu\u00b3 ba\u2074\u00b2 k\u00e3\u2074 ba\u00b3."
      },
      "a32_SURFACE2": {
        "lineref": "a32_SURFACE2",
        "start": 75.889,
        "stop": 79.697,
        "value": "T\u00e3\u2074\u00b2 ku\u2074n\u0129\u00b2 ko\u00b3o\u00b3 yu\u00b9ku\u00b9 t\u0169\u2074 i\u00b3ta\u00b2 <i>pastora</i> sa\u00b3k\u00e3\u2074 ku\u2074n\u0129\u00b2 ko\u00b3o\u00b3 tu\u00b3 yu\u00b9ku\u00b9 t\u0169\u2074 k\u00e3\u2074 ba\u00b3."
      },
      "a34_SURFACE2": {
        "lineref": "a34_SURFACE2",
        "start": 79.697,
        "stop": 86.903,
        "value": "A\u00b9be\u00b3, sa\u00b3k\u00e3\u2074 \u1ef9\u00e3\u2074\u00e3\u00b2 ya\u00b9 kwi\u2074i\u00b2\u2074 ba\u2074li\u2074 ba\u2074\u00b2 k\u00e3\u2074."
      },
      "a35_SURFACE2": {
        "lineref": "a35_SURFACE2",
        "start": 86.903,
        "stop": 96.045,
        "value": "Ndi\u00b3k\u1ef9\u00e3\u2074\u00b2 k\u00e3\u2074 nda\u2074ka\u00b3ya\u00b2n\u00e3\u00b9 tu\u2074u\u00b2yu\u00b9 a\u00b9chi\u00b9 ndi\u2074 t\u00e3&#039;\u00b9\u2074\u00e3\u00b2 chya&#039;\u00b3a\u00b2. A\u00b9chi\u00b9 ndi\u2074 ya\u00b9 i\u2074yo\u00b2 ndi\u00b3k\u0129\u2074 ba\u2074\u00b2 m\u0129\u2074\u0129\u2074 i\u2074yo\u00b2, m\u0129\u2074\u0129\u2074 i\u2074yo\u00b2 i\u00b3te\u00b2 k\u00e3\u2074 i\u00b3k\u00e3\u2074 ndwa\u2074a\u00b9\u00b3\u00b2 i\u2074chya\u00b9 t\u00e3\u00b3 i\u00b3k\u00e3\u2074 nda\u00b3ka\u00b3ya\u00b2n\u1ebd\u00b9 ko\u2074..., ko\u2074ndwa\u00b2 ta\u00b3ta\u00b2n\u00e3\u00b9."
      },
      "a37_SURFACE2": {
        "lineref": "a37_SURFACE2",
        "start": 96.045,
        "stop": 104.113,
        "value": "In\u00b3ka\u2074chi\u00b9 chi&#039;\u2074i\u2074n\u1ebd\u00b2 j\u0129&#039;\u2074\u0129\u2074 t\u0169\u2074 i\u00b3ta\u00b2 kw\u00e3\u00b9\u00f5\u2074 ba\u00b3 tu\u2074u\u00b2yu\u00b9 \u0129\u00b3\u0129\u00b3 tyem\u2074pu\u00b2."
      },
      "a38_SURFACE2": {
        "lineref": "a38_SURFACE2",
        "start": 104.113,
        "stop": 111.448,
        "value": "I\u00b3\u0129\u00b3 tyem\u2074pu\u00b2 ya\u00b9 k\u00e3\u2074 ndi\u2074 ndu\u2074te\u00b9 t\u00e3\u00b3 ja\u2074chw\u0303\u00e3\u2074\u00e3\u00b2 j\u0129&#039;\u2074\u0129\u2074n\u00e3\u00b2 ya\u00b9, ya\u00b9 bi\u00b3ko\u2074 i\u00b3ta\u00b2 ka\u2074chyo\u00b2\u2074 k\u00e3\u2074 a\u00b9chi\u00b9, sa\u00b3k\u00e3\u2074 ba\u2074\u00b2 ji\u2074n\u0129\u00b2 yu&#039;\u00b9u\u00b9 be\u00b2 r\u00e3\u2074, kwa\u00b9\u2074a\u00b2 ji\u2074n\u0129\u00b2yu\u00b9 tyem\u2074pu\u00b2 bi\u00b3t\u0129\u00b3 ndi\u2074,"
      },
      "a40_SURFACE2": {
        "lineref": "a40_SURFACE2",
        "start": 111.448,
        "stop": 113.478,
        "value": "Ba\u00b9\u2074\u00b3 xi\u2074ywa\u00b9\u00b3\u00b2 yu\u00b3m\u0129\u2074."
      },
      "a41_SURFACE2": {
        "lineref": "a41_SURFACE2",
        "start": 113.478,
        "stop": 117.752,
        "value": "Ji\u00b9\u2074ndyo\u00b2\u2074 sa\u00b9a\u00b3 a\u00b3se\u00b2 n\u00e3\u2074 i\u2074yo\u00b2 ndi\u00b3k\u1ef9\u00e3\u2074\u00b2 t\u00e3\u00b3 chye&#039;\u00b3e\u2074\u00b2 ndi\u2074 xa\u00b3ku\u2074n\u0129\u2074\u00b2 xi\u2074ywa\u00b9\u00b3\u00b2 nywe\u00b3e\u00b2\u2074 ka\u00b9a\u00b3."
      },
      "a44_SURFACE2": {
        "lineref": "a44_SURFACE2",
        "start": 124.14,
        "stop": 127.012,
        "value": "Ra\u00fal n\u00e3\u00b3n\u0129\u2074\u00b2."
      },
      "a46_SURFACE2": {
        "lineref": "a46_SURFACE2",
        "start": 127.012,
        "stop": 130.175,
        "value": "U\u00b9bi\u00b9 xi\u00b3ko\u00b3 i\u00b9\u00f1\u0169\u00b9 kwi\u00b9ya\u00b9 ku\u2074u\u00b2."
      },
      "a48_SURFACE2": {
        "lineref": "a48_SURFACE2",
        "start": 130.175,
        "stop": 130.175,
        "value": "Yolox\u00f3chitl ku\u2074u\u2074 \u00f1\u0169\u00b3\u0169\u00b2yu\u00b9."
      }
    }
  },
  "RCG Traducci\u00f3n": {
    "display": "top",
    "color": "C57214",
    "lines": {
      "a50": {
        "lineref": "a18",
        "start": 0,
        "stop": 0,
        "value": "Cu\u00e9ntanos un poco sobre la flor de olote dom\u00e9stica."
      },
      "a51": {
        "lineref": "a19",
        "start": 7.1,
        "stop": 7.1,
        "value": "Cu\u00e1ntos tipos hay, d\u00f3nde hay, y en qu\u00e9 tiempo lo siembran."
      },
      "a52": {
        "lineref": "a20",
        "start": 11.972,
        "stop": 11.972,
        "value": "Para qu\u00e9 lo utilizan, c\u00f3mo son, y para qu\u00e9 se utilizan."
      },
      "a53": {
        "lineref": "a27",
        "start": 57.621,
        "stop": 57.621,
        "value": "\u00bfLo cosen en guirnaldas?"
      },
      "a54": {
        "lineref": "a29",
        "start": 64.875,
        "stop": 64.875,
        "value": "\u00bfY huele bien?"
      },
      "a55": {
        "lineref": "a33",
        "start": 79.697,
        "stop": 79.697,
        "value": "\u00bfAh, s\u00ed? Son como, son peque\u00f1os.  Y los cosen y, este, y c\u00f3mo recogen las semillas para sembrar?"
      },
      "a56": {
        "lineref": "a36",
        "start": 96.045,
        "stop": 96.045,
        "value": "Y \u00bflos siembran juntos con el cempaz\u00fachitl? Al mismo tiempo. \u00bfAh, s\u00ed?"
      },
      "a57": {
        "lineref": "a39",
        "start": 111.448,
        "stop": 111.448,
        "value": "\u00bfNo se da en temporada de seca?"
      },
      "a58": {
        "lineref": "a42",
        "start": 117.752,
        "stop": 117.752,
        "value": "\u00bfAh, s\u00ed? Y, este, eso es todo, pues. Bueno."
      },
      "a59": {
        "lineref": "a43",
        "start": 124.14,
        "stop": 124.14,
        "value": "\u00bfC\u00f3mo te llamas?"
      },
      "a60": {
        "lineref": "a45",
        "start": 127.012,
        "stop": 127.012,
        "value": "\u00bfCu\u00e1ntos a\u00f1os tienes?"
      },
      "a61": {
        "lineref": "a47",
        "start": 130.175,
        "stop": 131.876,
        "value": "\u00bfC\u00f3mo se llama tu pueblo?"
      },
      "a62": {
        "lineref": "a49",
        "start": 132.305,
        "stop": 132.313,
        "value": "S\u00ed, est\u00e1 bien."
      }
    }
  },
  "RFM Traducci\u00f3n": {
    "display": "top",
    "color": "F84316",
    "lines": {
      "a63": {
        "lineref": "a21",
        "start": 16.909,
        "stop": 16.909,
        "value": "La flor de olote dom\u00e9stica es la que se ocupa en las ofrendas en los altares junto con la flor de cempaz\u00fachitl en todo santo,"
      },
      "a64": {
        "lineref": "a22",
        "start": 24.331,
        "stop": 24.331,
        "value": "las siembran en el tiempo en el que se siembran las semillas de cempaz\u00fachitl."
      },
      "a65": {
        "lineref": "a23",
        "start": 31.243,
        "stop": 31.243,
        "value": "Aqu\u00ed en el pueblo no se dan muy bien, en otros lugares, quiz\u00e1 m\u00e1s fr\u00edos se dan las flores muy bonitas, pero aqu\u00ed en el pueblo se dan las flores muy peque\u00f1as, creo."
      },
      "a66": {
        "lineref": "a24",
        "start": 40.327,
        "stop": 40.327,
        "value": "Crece apenas as\u00ed, sus flores son muy peque\u00f1as, apenas as\u00ed y"
      },
      "a67": {
        "lineref": "a25",
        "start": 46.041,
        "stop": 46.041,
        "value": "esas flores son las que se llevan en los ofrendas junto con las flores de cempaz\u00fachitl en el tiempo de todo santo, se dan muy poco aqu\u00ed en el pueblo. No se da bien en este pueblo."
      },
      "a68": {
        "lineref": "a26",
        "start": 53.917,
        "stop": 53.917,
        "value": "Quiz\u00e1 no lo siembran, ni yo no lo siembro porque para eso se necesitan las semillas."
      },
      "a69": {
        "lineref": "a28",
        "start": 58.351,
        "stop": 58.351,
        "value": "S\u00ed, los cosen con un hilo delgado. Sus guirnaldas son delgadas porque sus flores son muy peque\u00f1as."
      },
      "a70": {
        "lineref": "a30",
        "start": 65.885,
        "stop": 65.885,
        "value": "S\u00ed tiene olor, huelen, sirven para llevarlas a ofrendar en los altares."
      },
      "a71": {
        "lineref": "a31",
        "start": 70.611,
        "stop": 70.611,
        "value": "Sus flores son rosas, hay rosas y rojas, esas tambi\u00e9n son de dos tipos."
      },
      "a72": {
        "lineref": "a32",
        "start": 75.889,
        "stop": 75.889,
        "value": "Se parecen a las hojas de la flor de pastora las hojas de \u00e9sa planta."
      },
      "a73": {
        "lineref": "a34",
        "start": 79.697,
        "stop": 86.903,
        "value": "S\u00ed asi son verdes, son peque\u00f1as."
      },
      "a74": {
        "lineref": "a35",
        "start": 86.903,
        "stop": 86.903,
        "value": "Recogen las semillas de esas flores creo, porque yo no la he sembrado. Porque tienen semillas, donde tiene sus flores las secan para recoger las semillas para sembrar."
      },
      "a75": {
        "lineref": "a37",
        "start": 96.045,
        "stop": 104.113,
        "value": "S\u00ed los siembran al mismo tiempo que el cempaz\u00fachitl."
      },
      "a76": {
        "lineref": "a38",
        "start": 104.113,
        "stop": 104.113,
        "value": "Al mismo tiempo se da, porque se ocupa en todo santo, s\u00e9 que se da en ese tiempo, no hay en esta temporada que yo sepa."
      },
      "a77": {
        "lineref": "a40",
        "start": 111.448,
        "stop": 113.478,
        "value": "No se da en temporada de seca."
      },
      "a78": {
        "lineref": "a41",
        "start": 113.478,
        "stop": 113.478,
        "value": "No sabemos si al sembrarla se va dar en este pueblo porque aqui se da muy poco."
      },
      "a79": {
        "lineref": "a44",
        "start": 124.14,
        "stop": 127.012,
        "value": "Me llamo Ra\u00fal."
      },
      "a80": {
        "lineref": "a46",
        "start": 127.012,
        "stop": 130.175,
        "value": "Tengo 46 a\u00f1os."
      },
      "a81": {
        "lineref": "a48",
        "start": 130.175,
        "stop": 132.313,
        "value": "Mi pueblo es Yolox\u00f3chitl."
      }
    }
  }
}
